genia/__init__.py
genia/agents/__init__.py
genia/agents/adhoc.py
genia/agents/agent.py
genia/agents/chat.py
genia/conversation/llm_conversation.py
genia/conversation/llm_conversation_in_memory_repository.py
genia/entry.py
genia/llm_function/__init__.py
genia/llm_function/llm_function.py
genia/llm_function/llm_function_repository.py
genia/llm_function/llm_functions_factory.py
genia/llm_function/llm_skill_function.py
genia/llm_function/open_api_function.py
genia/llm_function/python_function.py
genia/llm_function/url_function.py
genia/llm_function_lookup_strategy/__init__.py
genia/llm_function_lookup_strategy/llm_function_lookup_strategy.py
genia/main.py
genia/openai_plugins/openai_plugins_repository.py
genia/settings/prompts.toml
genia/settings/settings.toml
genia/settings_loader.py
genia/token_limiter/token_limiter_openai.py
genia/tool_validators/llm_tool_validator.py
genia/tools/__init__.py
genia/tools/argo/__init__.py
genia/tools/argo/argo_client.py
genia/tools/argo/workflow_template.json
genia/tools/aws_client/__init__.py
genia/tools/aws_client/aws_client.py
genia/tools/aws_client/cloudtrail/__init__.py
genia/tools/aws_client/cloudtrail/aws_client_cloudtrail.py
genia/tools/aws_client/ec2/__init__.py
genia/tools/aws_client/ec2/aws_client_ec2.py
genia/tools/aws_client/ecr/aws_client_ecr.py
genia/tools/aws_client/ecr/repository_info_collector.py
genia/tools/aws_client/ecs/__init__.py
genia/tools/aws_client/ecs/aws_client_ecs.py
genia/tools/aws_client/events/__init__.py
genia/tools/aws_client/events/aws_client_events.py
genia/tools/aws_client/iam/__init__.py
genia/tools/aws_client/iam/aws_client_iam.py
genia/tools/aws_client/lambdas/__init__.py
genia/tools/aws_client/lambdas/aws_client_lambda.py
genia/tools/aws_client/lambdas/docker/Dockerfile
genia/tools/aws_client/lambdas/docker/__init__.py
genia/tools/aws_client/lambdas/docker/docker-build.sh
genia/tools/aws_client/lambdas/docker/entrypoint.sh
genia/tools/aws_client/sqs/__init__.py
genia-0.4.0.dist-info/LICENSE
genia-0.4.0.dist-info/METADATA
genia-0.4.0.dist-info/WHEEL
genia-0.4.0.dist-info/entry_points.txt
genia-0.4.0.dist-info/RECORD
