Metadata-Version: 2.1
Name: genia
Version: 0.4.0
Summary: 
Author: Uri Shamay
Author-email: cmpxchg16@gmail.com
Requires-Python: >=3.11,<4.0
Classifier: Programming Language :: Python :: 3
Classifier: Programming Language :: Python :: 3.11
Requires-Dist: beautifulsoup4 (==4.12.2)
Requires-Dist: boto3 (==1.26.165)
Requires-Dist: bravado (>=11.0.3,<12.0.0)
Requires-Dist: docker (>=6.1.3,<7.0.0)
Requires-Dist: dynaconf (>=3.1.12,<4.0.0)
Requires-Dist: faiss-cpu (==1.7.4)
Requires-Dist: flask (>=2.3.2,<3.0.0)
Requires-Dist: gcloud (>=0.18.3,<0.19.0)
Requires-Dist: google-search-results (==2.4.2)
Requires-Dist: google-serp-api (==1.0.3)
Requires-Dist: gunicorn (>=20.1.0,<21.0.0)
Requires-Dist: jsonref (>=1.1.0,<2.0.0)
Requires-Dist: kubernetes (>=26.1.0,<27.0.0)
Requires-Dist: langchain (==0.0.220)
Requires-Dist: numpy (==1.25.0)
Requires-Dist: opa-python-client (>=1.3.4,<2.0.0)
Requires-Dist: openai (>=0.27.8,<0.28.0)
Requires-Dist: pandas (==2.0.2)
Requires-Dist: pdpyras (>=5.1.0,<6.0.0)
Requires-Dist: pygithub (>=1.59.0,<2.0.0)
Requires-Dist: python-dotenv (>=1.0.0,<2.0.0)
Requires-Dist: python-jenkins (>=1.8.0,<2.0.0)
Requires-Dist: pytz (==2023.3)
Requires-Dist: pyyaml (==6.0)
Requires-Dist: requests (==2.31.0)
Requires-Dist: slack-bolt (>=1.18.0,<2.0.0)
Requires-Dist: slack-sdk (>=3.21.3,<4.0.0)
Requires-Dist: streamlit (==1.24.0)
Requires-Dist: streamlit-chat (>=0.1.1,<0.2.0)
Requires-Dist: termcolor (==2.3.0)
Requires-Dist: tiktoken (==0.4.0)
Requires-Dist: trafilatura (>=1.6.1,<2.0.0)
Requires-Dist: traitlets (==5.9.0)
Requires-Dist: yfinance (==0.2.22)
